django_progress-1.0.4.dist-info/DESCRIPTION.rst
django_progress-1.0.4.dist-info/METADATA
django_progress-1.0.4.dist-info/RECORD
django_progress-1.0.4.dist-info/WHEEL
django_progress-1.0.4.dist-info/metadata.json
django_progress-1.0.4.dist-info/top_level.txt
djprogress/__init__.py
djprogress/admin.py
djprogress/models.py
djprogress/urls.py
djprogress/views.py
djprogress/migrations/0001_initial.py
djprogress/migrations/__init__.py
djprogress/south_migrations/0001_initial.py
djprogress/south_migrations/0002_auto__add_field_progress_parent.py
djprogress/south_migrations/0003_auto__add_field_progress_exception.py
djprogress/south_migrations/__init__.py
djprogress/templates/djprogress/base.html
djprogress/templates/djprogress/inc_ajax_progress.html
djprogress/templates/djprogress/overview.html
djprogress_test_project/__init__.py
djprogress_test_project/manage.py
djprogress_test_project/settings.py
djprogress_test_project/urls.py
