Metadata-Version: 2.0
Name: django-progress
Version: 1.0.4
Summary: Django Progress
Home-page: http://github.com/vikingco/django-progress
Author: Jef Geskens, Unleashed NV
Author-email: operations@unleashed.be
License: BSD
Platform: UNKNOWN
Classifier: Intended Audience :: Developers
Classifier: Programming Language :: Python
Classifier: Operating System :: OS Independent
Classifier: Environment :: Web Environment
Classifier: Framework :: Django
